design.sv

module vendingmachine(clk,money,reset,states,choice,delivery,change);
  input [3:0]money;
  input [1:0]reset;
  input [1:0]choice;
  parameter s0=3'b000,s1=3'b001,s2=3'b010,s3=3'b011,s4=3'b100,s5=3'b101;
  output reg [1:0]delivery;
  output reg [3:0]change;
  output reg [2:0]states;
  input clk;
  always @ (posedge clk)
    begin
      case(states)
        s0:begin
          if(choice==2'b01)
            begin
              states<=s1;
              delivery<=1'b0;
              change<=4'b0000;
            end
          else if(choice==2'b10)
            begin
              states<=s4;
              delivery<=1'b0;
              change<=4'b0000;
            end
          else
            begin
              $display(" INVALID CHOICE ");
            end
        end
        s1:begin
          if(money==4'b0000)
            begin
              states<=s1;
              delivery<=1'b0;
              change<=4'b0000;
            end
          else if(money==4'b1010)
            begin
              states<=s3;
              delivery<=1'b1;
              change<=4'b0000;
            end
          else if(money==4'b0101)
            begin
              states<=s2;
              delivery<=1'b0;
              change<=4'b0000;
            end
          else
            begin
              $display(" PUT IN A VALID DENOMINATION ");
            end
        end
        s3:begin
          if(reset==1'b1)
            begin
              states<=s0;
              delivery<=1'b0;
              change<=4'b0000;
            end
          else if(money==4'b1010)
            begin
              states<=s3;
              delivery<=1'b1;
              change<=4'b0000;
            end
          else if(money==4'b0101)
            begin
              states<=s2;
              delivery<=1'b0;
              change<=4'b0000;
            end
          else
            begin
              $display(" PUT IN A VALID CHOICE ");
            end
        end
        s4:begin
          if(money==0)
            begin
              states<=s4;
              delivery<=1'b0;
              change<=4'b0000;
            end
          else if(money==4'b0101)
            begin
              states<=s5;
              delivery<=1'b1;
              change<=4'b0000;
            end
          else if(money==4'b1010)
            begin
              states<=s5;
              delivery<=1'b1;
              change<=4'b0101;
            end
        end
         s5:begin
          if(reset==1'b1)
            begin
              states<=s0;
              delivery<=1'b0;
              change<=4'b0000;
            end
          else if(money==4'b1010)
            begin
              states<=s5;
              delivery<=1'b1;
              change<=4'b0101;
            end
          else if(money==4'b0101)
            begin
              states<=s5;
              delivery<=1'b1;
              change<=4'b0000;
            end
           else if(money==4'b0000)
             begin
               states<=s4;
               delivery<=1'b0;
               change<=4'b0000;
             end
          else
            begin
              $display(" PUT IN A VALID CHOICE ");
            end
        end
        default:begin
          if(choice==2'b01)
            begin
              states<=s1;
              delivery<=1'b0;
              change<=4'b0000;
            end
          else if(choice==2'b10)
            begin
              states<=s4;
              delivery<=1'b0;
              change<=4'b0000;
            end
          else
            begin
              $display(" INVALID CHOICE ");
            end
        end
      endcase
    end
endmodule

testbench.sv
module tb;
  reg [1:0]clk;
  reg [3:0]money;
  reg [1:0]reset;
  reg [1:0]choice;
  wire [1:0]delivery;
  wire [3:0]change;
  wire [2:0]states;
  vendingmachine v0(clk,money,reset,states,choice,delivery,change);
  always #5 clk=~clk;
  initial
    begin
      $dumpfile("vendingmachine.vcd");
      $dumpvars(0,tb);
      $monitor($time," Money=%b Choice=%b Reset=%b State=%b Delivery=%b Change=%b ",money,choice,reset,states,delivery,change);
    end
  initial
    begin
      clk<=1'b0;
      #5;
      choice<=2'b10;
      reset<=1'b0;
      #10;
      money<=4'b1010;
      reset<=1'b0;
      #10;
      reset<=1'b1;
      #10 $finish;
    end
endmodule

vendingmachine.vcd
$date
	Thu Sep 21 11:10:12 2023
$end
$version
	Icarus Verilog
$end
$timescale
	1s
$end
$scope module tb $end
$var wire 4 ! change [3:0] $end
$var wire 2 " delivery [1:0] $end
$var wire 3 # states [2:0] $end
$var reg 2 $ choice [1:0] $end
$var reg 2 % clk [1:0] $end
$var reg 4 & money [3:0] $end
$var reg 2 ' reset [1:0] $end
$scope module v0 $end
$var wire 2 ( choice [1:0] $end
$var wire 1 ) clk $end
$var wire 4 * money [3:0] $end
$var wire 2 + reset [1:0] $end
$var reg 4 , change [3:0] $end
$var reg 2 - delivery [1:0] $end
$var reg 3 . states [2:0] $end
$upscope $end
$upscope $end
$enddefinitions $end
#0
$dumpvars
bx .
bx -
bx ,
bx +
bx *
0)
bx (
bx '
bx &
b0 %
bx $
bx #
bx "
bx !
$end
#5
b0 '
b0 +
b10 $
b10 (
1)
b11 %
#10
0)
b0 %
#15
b0 ,
b0 !
b0 -
b0 "
b100 .
b100 #
b1010 &
b1010 *
1)
b11 %
#20
0)
b0 %
#25
b101 ,
b101 !
b1 -
b1 "
b101 .
b101 #
b1 '
b1 +
1)
b11 %
#30
0)
b0 %
#35
b0 ,
b0 !
b0 -
b0 "
b0 .
b0 #
1)
b11 %
